ship_cert_gen/__init__.py
ship_cert_gen/__main__.py
ship_cert_gen/gen.py
ship_cert_gen/test_gen.py
ship_cert_gen-1.0.3.dist-info/LICENSE
ship_cert_gen-1.0.3.dist-info/METADATA
ship_cert_gen-1.0.3.dist-info/WHEEL
ship_cert_gen-1.0.3.dist-info/top_level.txt
ship_cert_gen-1.0.3.dist-info/RECORD
