Metadata-Version: 2.2
Name: ship-cert-gen
Version: 1.0.3
Summary: Generates a Self-Signed SHIP Certificate + SKI
Author-email: laurenzfg <www@laurenzfg.com>
Project-URL: Repository, https://github.com/laurenzfg/ship-cert-gen
Classifier: Intended Audience :: Developers
Classifier: License :: OSI Approved :: MIT License
Classifier: Programming Language :: Python :: 3
Requires-Python: >=3.8
License-File: LICENSE
Requires-Dist: cryptography~=44.0.0
Provides-Extra: dev-requirements
Requires-Dist: pytest; extra == "dev-requirements"
Requires-Dist: setuptools; extra == "dev-requirements"
Requires-Dist: wheel; extra == "dev-requirements"
